BlaiseKnapsack.py
BlaiseKnapsack-0.0.1.dist-info/LICENSE.txt
BlaiseKnapsack-0.0.1.dist-info/METADATA
BlaiseKnapsack-0.0.1.dist-info/WHEEL
BlaiseKnapsack-0.0.1.dist-info/top_level.txt
BlaiseKnapsack-0.0.1.dist-info/RECORD
