Metadata-Version: 2.1
Name: BlaiseKnapsack
Version: 0.0.1
Summary: Greedy Algorithm for the knapsack problem
Home-page: https://github.com/Blaise143/Knapsack-Optimization
Author: Blaise Appolinary
Author-email: blaiseappol@gmail.com
License: UNKNOWN
Platform: UNKNOWN
License-File: LICENSE.txt
